pfh/glidersim/__init__.py
pfh/glidersim/_fast_interp.py
pfh/glidersim/_version.py
pfh/glidersim/airfoil.py
pfh/glidersim/foil.py
pfh/glidersim/foil_aerodynamics.py
pfh/glidersim/foil_layout.py
pfh/glidersim/foil_sections.py
pfh/glidersim/orientation.py
pfh/glidersim/paraglider.py
pfh/glidersim/paraglider_harness.py
pfh/glidersim/paraglider_wing.py
pfh/glidersim/simulator.py
pfh/glidersim/util.py
pfh/glidersim/extras/__init__.py
pfh/glidersim/extras/airfoils.py
pfh/glidersim/extras/compute_polars.py
pfh/glidersim/extras/plots.py
pfh/glidersim/extras/simulation.py
pfh/glidersim/extras/wings.py
pfh/glidersim/extras/data/NACA23015_N5.0/gridded.csv
pfh/glidersim/extras/data/NACA23015_N7.0/gridded.csv
pfh/glidersim/extras/data/braking_NACA24018_Xtr0.25/NACA24018_theta30_Ku4.5_Kl0.5_d0.00_deltad0.00000.dat
pfh/glidersim/extras/data/braking_NACA24018_Xtr0.25/NACA24018_theta30_Ku4.5_Kl0.5_d0.07_deltad0.02691.dat
pfh/glidersim/extras/data/braking_NACA24018_Xtr0.25/NACA24018_theta30_Ku4.5_Kl0.5_d0.10_deltad0.04182.dat
pfh/glidersim/extras/data/braking_NACA24018_Xtr0.25/NACA24018_theta30_Ku4.5_Kl0.5_d0.14_deltad0.05809.dat
pfh/glidersim/extras/data/braking_NACA24018_Xtr0.25/NACA24018_theta30_Ku4.5_Kl0.5_d0.17_deltad0.07605.dat
pfh/glidersim/extras/data/braking_NACA24018_Xtr0.25/NACA24018_theta30_Ku4.5_Kl0.5_d0.21_deltad0.09606.dat
pfh/glidersim/extras/data/braking_NACA24018_Xtr0.25/NACA24018_theta30_Ku4.5_Kl0.5_d0.24_deltad0.11845.dat
pfh/glidersim/extras/data/braking_NACA24018_Xtr0.25/NACA24018_theta30_Ku4.5_Kl0.5_d0.28_deltad0.14353.dat
pfh/glidersim/extras/data/braking_NACA24018_Xtr0.25/NACA24018_theta30_Ku4.5_Kl0.5_d0.31_deltad0.17156.dat
pfh/glidersim/extras/data/braking_NACA24018_Xtr0.25/NACA24018_theta30_Ku4.5_Kl0.5_d0.35_deltad0.20274.dat
pfh/glidersim/extras/data/braking_NACA24018_Xtr0.25/README
pfh/glidersim/extras/data/braking_NACA24018_Xtr0.25/nonuniform_grid.csv
pfh/glidersim/extras/data/braking_NACA24018_Xtr0.25/resample.py
pfh.glidersim-2022.3.0a0.dist-info/LICENSE.txt
pfh.glidersim-2022.3.0a0.dist-info/METADATA
pfh.glidersim-2022.3.0a0.dist-info/WHEEL
pfh.glidersim-2022.3.0a0.dist-info/top_level.txt
pfh.glidersim-2022.3.0a0.dist-info/RECORD
