Metadata-Version: 2.1
Name: pfh.glidersim
Version: 2022.3.0a0
Summary: A library for paraglider dynamics modeling and simulation
Home-page: https://github.com/pfheatwole/glidersim
Author: Peter Heatwole
Author-email: pfheatwole@gmail.com
License: MIT
Project-URL: Documentation, https://pfheatwole.github.io/glidersim
Project-URL: Discussions, https://github.com/pfheatwole/glidersim/discussions
Project-URL: Issue Tracker, https://github.com/pfheatwole/glidersim/issues
Platform: UNKNOWN
Classifier: Development Status :: 3 - Alpha
Classifier: License :: OSI Approved :: MIT License
Classifier: Operating System :: OS Independent
Classifier: Topic :: Scientific/Engineering :: Physics
Classifier: Intended Audience :: Science/Research
Classifier: Programming Language :: Python :: 3
Classifier: Programming Language :: Python :: 3.8
Classifier: Programming Language :: Python :: 3.9
Classifier: Programming Language :: Python :: 3.10
Requires-Python: >=3.8
License-File: LICENSE.txt
Requires-Dist: numpy (>=1.20)
Requires-Dist: scipy
Requires-Dist: numba (>=0.54)
Requires-Dist: matplotlib
Provides-Extra: dev
Requires-Dist: flake8 ; extra == 'dev'
Requires-Dist: flake8-bugbear ; extra == 'dev'
Requires-Dist: flake8-comprehensions ; extra == 'dev'
Requires-Dist: flake8-docstrings ; extra == 'dev'
Requires-Dist: flake8-rst-docstrings ; extra == 'dev'
Requires-Dist: pre-commit ; extra == 'dev'
Requires-Dist: mypy ; extra == 'dev'
Requires-Dist: pytest ; extra == 'dev'
Requires-Dist: Sphinx (>=4.4.0) ; extra == 'dev'
Requires-Dist: furo (>=2022.2.14.1) ; extra == 'dev'
Requires-Dist: numpydoc ; extra == 'dev'
Requires-Dist: sphinx-autobuild ; extra == 'dev'
